[
  {
    "title": "001 . cut  by  love  bobo marley",
    "url": "https://archive.org/download/1837293464717627648/001%20.%20cut%20%20by%20%20love%20%20bobo%20marley~1.mp3"
  },
  {
    "title": "002 . go pato  pato baton",
    "url": "https://archive.org/download/1837293464717627648/002%20.%20go%20pato%20%20pato%20baton~1.mp3"
  },
  {
    "title": "003 . Jessica Jay - Casablanca",
    "url": "https://archive.org/download/1837293464717627648/003%20.%20Jessica%20Jay%20-%20Casablanca~1.mp3"
  },
  {
    "title": "004 . raicing  my familile  steven  k",
    "url": "https://archive.org/download/1837293464717627648/004%20.%20raicing%20%20my%20familile%20%20steven%20%20k~1.mp3"
  },
  {
    "title": "005 . red red  wine   ub40",
    "url": "https://archive.org/download/1837293464717627648/005%20.%20red%20red%20%20wine%20%20%20ub40~1.mp3"
  },
  {
    "title": "006 . bad boys  iner circle",
    "url": "https://archive.org/download/1837293464717627648/006%20.%20bad%20boys%20%20iner%20circle~1.mp3"
  },
  {
    "title": "007 . samba reggae  jimmy clip",
    "url": "https://archive.org/download/1837293464717627648/007%20.%20samba%20reggae%20%20jimmy%20clip~1.mp3"
  },
  {
    "title": "008 . coco nut´s  dancing   margarita",
    "url": "https://archive.org/download/1837293464717627648/008%20.%20coco%20nut%C2%B4s%20%20dancing%20%20%20margarita~1.mp3"
  },
  {
    "title": "009 . Summer Summer  Loft",
    "url": "https://archive.org/download/1837293464717627648/009%20.%20Summer%20Summer%20%20Loft~1.mp3"
  },
  {
    "title": "010 . sobany  ibola letho",
    "url": "https://archive.org/download/1837293464717627648/010%20.%20sobany%20%20ibola%20letho~1.mp3"
  },
  {
    "title": "011 . te vi bailando  jakida",
    "url": "https://archive.org/download/1837293464717627648/011%20.%20te%20vi%20bailando%20%20jakida~1.mp3"
  },
  {
    "title": "012. pase lo que pase   big boy",
    "url": "https://archive.org/download/1837293464717627648/012.%20pase%20lo%20que%20pase%20%20%20big%20boy~1.mp3"
  },
  {
    "title": "013 . wen a tu wodeer  clifp",
    "url": "https://archive.org/download/1837293464717627648/013%20.%20wen%20a%20tu%20wodeer%20%20clifp~1.mp3"
  },
  {
    "title": "014 . reggae cogonna  gag   dr albam",
    "url": "https://archive.org/download/1837293464717627648/014%20.%20reggae%20cogonna%20%20gag%20%20%20dr%20albam~1.mp3"
  },
  {
    "title": "015 . coco jambo  mr precident",
    "url": "https://archive.org/download/1837293464717627648/015%20.%20coco%20jambo%20%20mr%20precident~1.mp3"
  },
  {
    "title": "016 . every dance  dj bobo",
    "url": "https://archive.org/download/1837293464717627648/016%20.%20every%20dance%20%20dj%20bobo~1.mp3"
  },
  {
    "title": "017. elevation randy bush",
    "url": "https://archive.org/download/1837293464717627648/017.%20elevation%20randy%20bush~1.mp3"
  },
  {
    "title": "018 . foreigan  affair  randy bush",
    "url": "https://archive.org/download/1837293464717627648/018%20.%20foreigan%20%20affair%20%20randy%20bush~1.mp3"
  },
  {
    "title": "019 . chica baila chica exclusivo",
    "url": "https://archive.org/download/1837293464717627648/019%20.%20chica%20baila%20chica%20exclusivo~1.mp3"
  },
  {
    "title": "020 . Masterboy   Land Of Dreaming",
    "url": "https://archive.org/download/1837293464717627648/020%20.%20Masterboy%20%20%20Land%20Of%20Dreaming~1.mp3"
  },
  {
    "title": "021 .  rock wit  you inner circle",
    "url": "https://archive.org/download/1837293464717627648/021%20.%20%20rock%20wit%20%20you%20inner%20circle~1.mp3"
  },
  {
    "title": "022 . all the  she winst  ace of bace L",
    "url": "https://archive.org/download/1837293464717627648/022%20.%20all%20the%20%20she%20winst%20%20ace%20of%20bace%20L~1.mp3"
  },
  {
    "title": "022 . cuiddy  gogo  ray bice",
    "url": "https://archive.org/download/1837293464717627648/022%20.%20cuiddy%20%20gogo%20%20ray%20bice~1.mp3"
  },
  {
    "title": "023 . a way  from  home  dr albam",
    "url": "https://archive.org/download/1837293464717627648/023%20.%20a%20way%20%20from%20%20home%20%20dr%20albam~1.mp3"
  },
  {
    "title": "024 . chica bom bom  joselito",
    "url": "https://archive.org/download/1837293464717627648/024%20.%20chica%20bom%20bom%20%20joselito~1.mp3"
  },
  {
    "title": "025 . is this  love bob marley",
    "url": "https://archive.org/download/1837293464717627648/025%20.%20is%20this%20%20love%20bob%20marley~1.mp3"
  },
  {
    "title": "026 .  Sweet Harmony The Beloved",
    "url": "https://archive.org/download/1837293464717627648/026%20.%20%20Sweet%20Harmony%20The%20Beloved~1.mp3"
  },
  {
    "title": "027 . loco de atar  zimbawe",
    "url": "https://archive.org/download/1837293464717627648/027%20.%20loco%20de%20atar%20%20zimbawe~1.mp3"
  },
  {
    "title": "028 . jambo jambo mr precident",
    "url": "https://archive.org/download/1837293464717627648/028%20.%20jambo%20jambo%20mr%20precident~1.mp3"
  },
  {
    "title": "029 . deja que el ritmo continue 12_ - dr alban",
    "url": "https://archive.org/download/1837293464717627648/029%20.%20deja%20que%20el%20ritmo%20continue%2012_%20-%20dr%20alban~1.mp3"
  },
  {
    "title": "030 . prque te vas  masrtey boys",
    "url": "https://archive.org/download/1837293464717627648/030%20.%20prque%20te%20vas%20%20masrtey%20boys~1.mp3"
  },
  {
    "title": "031 .  Hung Up     Madonna",
    "url": "https://archive.org/download/1837293464717627648/031%20.%20%20Hung%20Up%20%20%20%20%20Madonna~1.mp3"
  },
  {
    "title": "032 . living  on ny  own  freddy mercury",
    "url": "https://archive.org/download/1837293464717627648/032%20.%20living%20%20on%20ny%20%20own%20%20freddy%20mercury~1.mp3"
  },
  {
    "title": "033 . waht is love  hadaway",
    "url": "https://archive.org/download/1837293464717627648/033%20.%20waht%20is%20love%20%20hadaway~1.mp3"
  },
  {
    "title": "034 . Wheel Of Fortune (12_ Mix) Ace Of Base",
    "url": "https://archive.org/download/1837293464717627648/034%20.%20Wheel%20Of%20Fortune%20%2812_%20Mix%29%20Ace%20Of%20Base%20%20~1.mp3"
  },
  {
    "title": "035 .  techno el  pato  exclusivo",
    "url": "https://archive.org/download/1837293464717627648/035%20.%20%20techno%20el%20%20pato%20%20exclusivo%20~1.mp3"
  },
  {
    "title": "036 . eberybody  blue  sisten",
    "url": "https://archive.org/download/1837293464717627648/036%20.%20eberybody%20%20%20blue%20%20sisten%20~1.mp3"
  },
  {
    "title": "037 . suena como una melodia  randy bush",
    "url": "https://archive.org/download/1837293464717627648/037%20.%20suena%20como%20una%20melodia%20%20randy%20bush%20~1.mp3"
  },
  {
    "title": "038 . la vida es nek",
    "url": "https://archive.org/download/1837293464717627648/038%20.%20la%20vida%20es%20nek%20~1.mp3"
  },
  {
    "title": "039 . sobreviviendo ment  and  word",
    "url": "https://archive.org/download/1837293464717627648/039%20.%20sobreviviendo%20ment%20%20and%20%20word%20~1.mp3"
  },
  {
    "title": "040 . self  control  raf",
    "url": "https://archive.org/download/1837293464717627648/040%20.%20self%20%20control%20%20raf%20~1.mp3"
  },
  {
    "title": "041 . el mas sensual  exclusivo",
    "url": "https://archive.org/download/1837293464717627648/041%20.%20el%20mas%20sensual%20%20exclusivo%20~1.mp3"
  },
  {
    "title": "042 . samba reggae  exlcuvio",
    "url": "https://archive.org/download/1837293464717627648/042%20.%20samba%20reggae%20%20exlcuvio%20~1.mp3"
  },
  {
    "title": "043 . mis ojos  lloran por ti  big boy",
    "url": "https://archive.org/download/1837293464717627648/043%20.%20mis%20ojos%20%20lloran%20por%20ti%20%20big%20boy%20~1.mp3"
  },
  {
    "title": "044 . wear you to the balla ub 40",
    "url": "https://archive.org/download/1837293464717627648/044%20.%20wear%20you%20to%20the%20balla%20ub%2040%20~1.mp3"
  },
  {
    "title": "045 . swear  iner sircle",
    "url": "https://archive.org/download/1837293464717627648/045%20.%20swear%20%20iner%20sircle%20~1.mp3"
  },
  {
    "title": "046. techno galaxia  dj star",
    "url": "https://archive.org/download/1837293464717627648/046.%20techno%20galaxia%20%20dj%20star%20~1.mp3"
  },
  {
    "title": "047 . beso arabe  tarkan",
    "url": "https://archive.org/download/1837293464717627648/047%20.%20beso%20arabe%20%20tarkan%20~1.mp3"
  },
  {
    "title": "048. limbo reggae  el simbolo",
    "url": "https://archive.org/download/1837293464717627648/048.%20limbo%20reggae%20%20el%20simbolo%20~1.mp3"
  },
  {
    "title": "049 . lust dance reggae  gigi agostino",
    "url": "https://archive.org/download/1837293464717627648/049%20.%20lust%20dance%20reggae%20%20gigi%20agostino%20~1.mp3"
  },
  {
    "title": "050 . ther ere  randi bush",
    "url": "https://archive.org/download/1837293464717627648/050%20.%20ther%20ere%20%20randi%20bush%20~1.mp3"
  }
]
